wdb_utils/__init__.py
wdb_utils/connections.py
wdb_utils/handlers.py
wdb_utils-3.7.4.dist-info/METADATA
wdb_utils-3.7.4.dist-info/WHEEL
wdb_utils-3.7.4.dist-info/top_level.txt
wdb_utils-3.7.4.dist-info/RECORD
