Metadata-Version: 2.4
Name: wdb_utils
Version: 3.7.4
Summary: Utilities for querying and loading data into an Oracle, Snowflake, or Postgres database.
Author: Courtney Wade
Project-URL: Homepage, https://github.com/cwade/wdb_utils
Project-URL: Repository, https://github.com/cwade/wdb_utils
Keywords: pandas,oracle,postgres,snowflake,query,database
Classifier: Programming Language :: Python :: 3
Classifier: Operating System :: OS Independent
Requires-Python: >=3.7
Requires-Dist: oracledb>=1.2
Requires-Dist: pandas>=2.0
Requires-Dist: PyYAML>=6.0
Requires-Dist: snowflake-connector-python>=3.15.0
Requires-Dist: psycopg2-binary>=2.9
